{
  "source": "pubmed",
  "query": {
    "drug": "Cyproterone acetate",
    "disease": "migraine with brainstem aura",
    "query_string": "Cyproterone acetate AND migraine with brainstem aura"
  },
  "data": {
    "query": "Cyproterone acetate AND migraine with brainstem aura",
    "results": [
      {
        "pmid": "25227335",
        "title": "Hormonal contraception, thrombosis and age.",
        "abstract": "This paper reviews the risk of thrombosis with use of different types of hormonal contraception in women of different ages.",
        "journal": "Expert opinion on drug safety",
        "year": "2014",
        "authors": [
          "Lidegaard Øjvind"
        ],
        "pub_types": [
          "Journal Article",
          "Review"
        ],
        "mesh_terms": [
          "Adult",
          "Age Factors",
          "Contraceptives, Oral, Combined",
          "Contraceptives, Oral, Hormonal",
          "Female",
          "Genetic Predisposition to Disease",
          "Humans",
          "Myocardial Infarction",
          "Progestins",
          "Risk Factors"
        ],
        "url": "https://pubmed.ncbi.nlm.nih.gov/25227335/"
      },
      {
        "pmid": "30389542",
        "title": "[Hormonal contraception and vascular risk: CNGOF Contraception Guidelines].",
        "abstract": "Venous thromboembolism and arterial ischemic events are the main deleterious diseases associated with the use of combined hormonal contraceptives (CHC). Even though their composition has been substantially improved, the vascular risk persists with the most recent CHCs use. If the vascular risk associated with CHCs containing 50μg EE is significantly higher than with those containing less than 50μg, there is no evidence that the CHCs containing either 30 or 20μg of EE induce different venous risks. CHC containing gestodene, desogestrel, drospirenone or cyproterone acetate are associated with a higher risk of venous thrombosis compared with levonorgestrel-containing CHCs. CHC containing norgestimate are associated with similar venous thrombosis risk than CHC containing levonorgestrel. Venous thrombosis risk of non-oral routes of administration of CHC appears to be equivalent to the risk of CHC containing gestodene or desogestrel, but this result is based on a small number of epidemiologi",
        "journal": "Gynecologie, obstetrique, fertilite & senologie",
        "year": "2018",
        "authors": [
          "Plu-Bureau G",
          "Sabbagh E",
          "Hugon-Rodin J"
        ],
        "pub_types": [
          "Journal Article",
          "Practice Guideline"
        ],
        "mesh_terms": [
          "Androstenes",
          "Contraceptive Agents, Female",
          "Contraceptives, Oral, Combined",
          "Contraceptives, Oral, Hormonal",
          "Cyproterone Acetate",
          "Desogestrel",
          "Female",
          "France",
          "Humans",
          "Levonorgestrel"
        ],
        "url": "https://pubmed.ncbi.nlm.nih.gov/30389542/"
      }
    ]
  },
  "timestamp": "2026-03-10T01:48:30.400532",
  "success": true,
  "error_message": null
}