{
  "source": "pubmed",
  "query": {
    "drug": "Gadobutrol",
    "disease": "peripheral vascular disease",
    "query_string": "Gadobutrol AND peripheral vascular disease"
  },
  "data": {
    "query": "Gadobutrol AND peripheral vascular disease",
    "results": [
      {
        "pmid": "26001243",
        "title": "MR Angiography at 3 T of Peripheral Arterial Disease: A Randomized Prospective Comparison of Gadoterate Meglumine and Gadobutrol.",
        "abstract": "This large-scale randomized study aimed to show the noninferiority in terms of diagnostic performance of gadoterate meglumine-enhanced versus gadobutrol-enhanced 3-T MR angiography (MRA) using digital subtraction angiography (DSA) as the reference standard in patients with peripheral arterial occlusive disease (PAOD).",
        "journal": "AJR. American journal of roentgenology",
        "year": "2015",
        "authors": [
          "Loewe Christian",
          "Arnaiz Javier",
          "Krause Denis",
          "Marti-Bonmati Luis",
          "Haneder Stefan"
        ],
        "pub_types": [
          "Clinical Trial, Phase IV",
          "Comparative Study",
          "Journal Article",
          "Randomized Controlled Trial",
          "Research Support, Non-U.S. Gov't"
        ],
        "mesh_terms": [
          "Adult",
          "Aged",
          "Aged, 80 and over",
          "Angiography, Digital Subtraction",
          "Arterial Occlusive Diseases",
          "Contrast Media",
          "Double-Blind Method",
          "Female",
          "Humans",
          "Image Enhancement"
        ],
        "url": "https://pubmed.ncbi.nlm.nih.gov/26001243/"
      },
      {
        "pmid": "12928960",
        "title": "Gadobutrol-enhanced moving-table magnetic resonance angiography in patients with peripheral vascular disease: a prospective, multi-centre blinded comparison with digital subtraction angiography.",
        "abstract": "The purpose of this study was to compare moving-table three-dimensional contrast-enhanced magnetic resonance angiography (CE MRA), using 1.0-mol gadobutrol, with intra-arterial digital subtraction angiography (i.a. DSA) for evaluation of pelvic and peripheral arteries in patients with peripheral arterial occlusive disease. A total of 203 patients were examined in a prospective, multi-centre study at 1.0/1.5 T. Ten vessel segments of one leg were evaluated on-site and by three independent blinded reviewers off-site. One hundred eighty-two patients were evaluable in blinded reading. For pelvis and thigh, there was statistically significant diagnostic agreement between CE MRA and i.a. DSA on-site (94%) and off-site (86-88%). Overall, for detection of clinically significant stenoses, 93% sensitivity and 90% specificity were achieved in on-site evaluation, with 71-76 and 87-93% off-site; for detection of occlusion, sensitivity and specificity on-site were 91 and 97%, with 75-82 and 94-98% o",
        "journal": "European radiology",
        "year": "2003",
        "authors": [
          "Hentsch Annette",
          "Aschauer Manuela A",
          "Balzer Jörn O",
          "Brossmann Joachim",
          "Busch Hans P"
        ],
        "pub_types": [
          "Clinical Trial",
          "Comparative Study",
          "Journal Article",
          "Multicenter Study"
        ],
        "mesh_terms": [
          "Angiography, Digital Subtraction",
          "Arterial Occlusive Diseases",
          "Contrast Media",
          "Double-Blind Method",
          "Female",
          "Humans",
          "Image Enhancement",
          "Leg",
          "Magnetic Resonance Angiography",
          "Male"
        ],
        "url": "https://pubmed.ncbi.nlm.nih.gov/12928960/"
      },
      {
        "pmid": "22848033",
        "title": "Comparison of 0.5 M gadoterate and 1.0 M gadobutrol in peripheral MRA: a prospective, single-center, randomized, crossover, double-blind study.",
        "abstract": "To evaluate the diagnostic efficacy of macrocyclic paramagnetic gadolinium (Gd) chelates gadoterate (0.5 mmol/mL) and gadobutrol (1.0 mmol/mL) for the diagnosis of clinically significant abdominal/lower limb arterial diseases at 3.0T.",
        "journal": "Journal of magnetic resonance imaging : JMRI",
        "year": "2012",
        "authors": [
          "Haneder Stefan",
          "Attenberger Ulrike I",
          "Schoenberg Stefan O",
          "Loewe Christian",
          "Arnaiz Javier"
        ],
        "pub_types": [
          "Comparative Study",
          "Journal Article",
          "Randomized Controlled Trial",
          "Research Support, Non-U.S. Gov't"
        ],
        "mesh_terms": [
          "Aged",
          "Contrast Media",
          "Cross-Over Studies",
          "Dose-Response Relationship, Drug",
          "Double-Blind Method",
          "Female",
          "Heterocyclic Compounds",
          "Humans",
          "Magnetic Resonance Angiography",
          "Male"
        ],
        "url": "https://pubmed.ncbi.nlm.nih.gov/22848033/"
      },
      {
        "pmid": "20959539",
        "title": "Peripheral arterial occlusive disease: evaluation of a high spatial and temporal resolution 3-T MR protocol with a low total dose of gadolinium versus conventional angiography.",
        "abstract": "To evaluate a peripheral magnetic resonance (MR) angiographic protocol combining continuous table movement (CTM) MR angiography of the entire runoff vasculature with time-resolved (TWIST) 3-T MR angiography of the calves with a total gadolinium dose of 0.1 mmol per kilogram of body weight.",
        "journal": "Radiology",
        "year": "2010",
        "authors": [
          "Attenberger Ulrike I",
          "Haneder Stefan",
          "Morelli John N",
          "Diehl Steffen J",
          "Schoenberg Stefan O"
        ],
        "pub_types": [
          "Evaluation Study",
          "Journal Article"
        ],
        "mesh_terms": [
          "Adult",
          "Aged",
          "Aged, 80 and over",
          "Angiography, Digital Subtraction",
          "Arterial Occlusive Diseases",
          "Contrast Media",
          "Female",
          "Humans",
          "Magnetic Resonance Angiography",
          "Male"
        ],
        "url": "https://pubmed.ncbi.nlm.nih.gov/20959539/"
      },
      {
        "pmid": "19652610",
        "title": "Peripheral magnetic resonance angiography with continuous table movement in combination with high spatial and temporal resolution time-resolved MRA With a total single dose (0.1 mmol/kg) of gadobutrol at 3.0 T.",
        "abstract": "To prove the concept of peripheral continuous table movement (CTM) MR-angiography (MRA) in combination with high spatial and temporal resolution time-resolved TWIST-MRA in a single MR-examination at 3.0 T with a single dose (0.1 mmol/kg) of gadobutrol in total.",
        "journal": "Investigative radiology",
        "year": "2009",
        "authors": [
          "Voth Matthias",
          "Haneder Stefan",
          "Huck Kurt",
          "Gutfleisch Alexandra",
          "Schönberg Stefan O"
        ],
        "pub_types": [
          "Journal Article"
        ],
        "mesh_terms": [
          "Adult",
          "Arterial Occlusive Diseases",
          "Contrast Media",
          "Female",
          "Humans",
          "Image Enhancement",
          "Image Interpretation, Computer-Assisted",
          "Imaging, Three-Dimensional",
          "Magnetic Resonance Angiography",
          "Male"
        ],
        "url": "https://pubmed.ncbi.nlm.nih.gov/19652610/"
      },
      {
        "pmid": "22777620",
        "title": "Triple-TWIST MRA: high spatial and temporal resolution MR angiography of the entire peripheral vascular system using a time-resolved 4D MRA technique.",
        "abstract": "Multi-station contrast-enhanced magnetic resonance angiography (MRA) is considered as the imaging investigation of first choice in patients suffering from peripheral arterial occlusive disease. In order to overcome venous overlay and to gain dynamic flow information as provided by digital subtraction angiography (DSA), we developed a triple injection protocol for high-resolution MRA of the entire peripheral vascular system, applying time-resolved (TR) four-dimensional (4D) MRA sequences.",
        "journal": "European radiology",
        "year": "2013",
        "authors": [
          "Kinner Sonja",
          "Quick Harald H",
          "Maderwald Stefan",
          "Hunold Peter",
          "Barkhausen Jörg"
        ],
        "pub_types": [
          "Comparative Study",
          "Journal Article"
        ],
        "mesh_terms": [
          "Adult",
          "Aged",
          "Aged, 80 and over",
          "Angiography, Digital Subtraction",
          "Arterial Occlusive Diseases",
          "Contrast Media",
          "Feasibility Studies",
          "Female",
          "Humans",
          "Magnetic Resonance Angiography"
        ],
        "url": "https://pubmed.ncbi.nlm.nih.gov/22777620/"
      },
      {
        "pmid": "24156379",
        "title": "Steady state vascular imaging with extracellular gadobutrol: evaluation of the additional diagnostic benefit in patients who have undergone a peripheral magnetic resonance angiography protocol.",
        "abstract": "To evaluate the feasibility and additional diagnostic benefit of a high-resolution steady state 3D-volume interpolated breath-hold exam (VIBE) sequence between a continuous table movement (CTM) MR angiography of the entire runoff vasculature and a time-resolved (TWIST) MRA of the calves.",
        "journal": "Journal of cardiovascular magnetic resonance : official journal of the Society for Cardiovascular Magnetic Resonance",
        "year": "2013",
        "authors": [
          "Ong Melissa M",
          "Hausotter Katharina",
          "Pilz Lothar R",
          "Schoenberg Stefan O",
          "Michaely Henrik J"
        ],
        "pub_types": [
          "Evaluation Study",
          "Journal Article"
        ],
        "mesh_terms": [
          "Adolescent",
          "Adult",
          "Age Factors",
          "Aged",
          "Aged, 80 and over",
          "Contrast Media",
          "Feasibility Studies",
          "Female",
          "Humans",
          "Lower Extremity"
        ],
        "url": "https://pubmed.ncbi.nlm.nih.gov/24156379/"
      },
      {
        "pmid": "12677513",
        "title": "[First clinical results in a study of contrast enhanced magnetic resonance angiography with the 1.0 molar gadobutrol in peripheral arterial occlusive disease--comparison to intraarterial DSA].",
        "abstract": "To assess the value of contrast enhanced (CE)-MR angiography (MRA) with 1.0 molar Gadobutrol (Schering, Germany) in comparison to intraarterial DSA in peripheral arterial occlusive disease (PAOD).",
        "journal": "RoFo : Fortschritte auf dem Gebiete der Rontgenstrahlen und der Nuklearmedizin",
        "year": "2003",
        "authors": [
          "Schäfer F K",
          "Schäfer P J",
          "Jahnke T",
          "Walluscheck K",
          "Priebe M"
        ],
        "pub_types": [
          "Comparative Study",
          "Evaluation Study",
          "Journal Article"
        ],
        "mesh_terms": [
          "Aged",
          "Aged, 80 and over",
          "Angiography, Digital Subtraction",
          "Arterial Occlusive Diseases",
          "Arteriosclerosis",
          "Contrast Media",
          "Female",
          "Femoral Artery",
          "Humans",
          "Iliac Artery"
        ],
        "url": "https://pubmed.ncbi.nlm.nih.gov/12677513/"
      },
      {
        "pmid": "21031523",
        "title": "Prospective comparison of image quality and diagnostic accuracy of 0.5 molar gadobenate dimeglumine and 1.0 molar gadobutrol in contrast-enhanced run-off magnetic resonance angiography of the lower extremities.",
        "abstract": "To compare image quality and diagnostic accuracy of 0.5 molar gadobenate dimeglumine and 1.0 molar gadobutrol in contrast-enhanced (CE) magnetic resonance angiography (MRA) of the lower extremities interindividually.",
        "journal": "Journal of magnetic resonance imaging : JMRI",
        "year": "2010",
        "authors": [
          "Achenbach Marina",
          "Figiel Jens H",
          "Burbelko Mykhaylo",
          "Heverhagen Johannes T"
        ],
        "pub_types": [
          "Comparative Study",
          "Journal Article",
          "Randomized Controlled Trial",
          "Research Support, Non-U.S. Gov't"
        ],
        "mesh_terms": [
          "Aged",
          "Arterial Occlusive Diseases",
          "Contrast Media",
          "Double-Blind Method",
          "Female",
          "Gadolinium DTPA",
          "Humans",
          "Lower Extremity",
          "Magnetic Resonance Angiography",
          "Male"
        ],
        "url": "https://pubmed.ncbi.nlm.nih.gov/21031523/"
      },
      {
        "pmid": "24893292",
        "title": "Enhancement characteristics and impact on image quality of two gadolinium chelates at equimolar doses for time-resolved 3-Tesla MR-angiography of the calf station.",
        "abstract": "To compare enhancement characteristics and image quality of two macrocyclic gadolinium chelates, gadoterate meglumine and gadobutrol, in low-dose, time-resolved MRA of the calf station.",
        "journal": "PloS one",
        "year": "2014",
        "authors": [
          "Hansmann Jan",
          "Michaely Henrik J",
          "Morelli John N",
          "Luckscheiter André",
          "Schoenberg Stefan O"
        ],
        "pub_types": [
          "Comparative Study",
          "Journal Article",
          "Research Support, Non-U.S. Gov't"
        ],
        "mesh_terms": [
          "Aged",
          "Contrast Media",
          "Female",
          "Humans",
          "Image Enhancement",
          "Magnetic Resonance Angiography",
          "Male",
          "Meglumine",
          "Middle Aged",
          "Organometallic Compounds"
        ],
        "url": "https://pubmed.ncbi.nlm.nih.gov/24893292/"
      },
      {
        "pmid": "18504760",
        "title": "1.0-M gadobutrol versus 0.5-M gadoterate for peripheral magnetic resonance angiography: a prospective randomized controlled clinical trial.",
        "abstract": "To perform a quantitative and qualitative comparison of gadobutrol and gadoterate in three-station contrast enhanced magnetic resonance angiography (CE-MRA) of the lower limbs.",
        "journal": "Journal of magnetic resonance imaging : JMRI",
        "year": "2008",
        "authors": [
          "Szucs-Farkas Zsolt",
          "Froehlich Johannes M",
          "Ulrich Martin",
          "Wuersten Hans-Ueli",
          "Guignard Dominique"
        ],
        "pub_types": [
          "Comparative Study",
          "Journal Article",
          "Randomized Controlled Trial"
        ],
        "mesh_terms": [
          "Aged",
          "Contrast Media",
          "Female",
          "Heterocyclic Compounds",
          "Humans",
          "Image Enhancement",
          "Imaging, Three-Dimensional",
          "Ischemia",
          "Leg",
          "Magnetic Resonance Angiography"
        ],
        "url": "https://pubmed.ncbi.nlm.nih.gov/18504760/"
      },
      {
        "pmid": "31321491",
        "title": "\"Myocardial transit-time\" (MyoTT): a novel and easy-to-perform CMR parameter to assess microvascular disease.",
        "abstract": "Myocardial microvascular disease may occur during the disease course of different cardiac as well as systemic disorders. With the present study, we introduce a novel and easy-to-perform cardiovascular magnetic resonance (CMR) parameter named \"myocardial transit-time\" (MyoTT).",
        "journal": "Clinical research in cardiology : official journal of the German Cardiac Society",
        "year": "2020",
        "authors": [
          "Chatzantonis Grigorios",
          "Bietenbeck Michael",
          "Florian Anca",
          "Meier Claudia",
          "Korthals Dennis"
        ],
        "pub_types": [
          "Journal Article"
        ],
        "mesh_terms": [
          "Adult",
          "Aged",
          "Blood Flow Velocity",
          "Cardiomyopathy, Hypertrophic",
          "Case-Control Studies",
          "Contrast Media",
          "Coronary Circulation",
          "Female",
          "Humans",
          "Magnetic Resonance Imaging, Cine"
        ],
        "url": "https://pubmed.ncbi.nlm.nih.gov/31321491/"
      },
      {
        "pmid": "15149986",
        "title": "Whole-body 3D MR angiography of patients with peripheral arterial occlusive disease.",
        "abstract": "We assessed the diagnostic performance of whole-body 3D contrast-enhanced MR angiography in comparison with digital subtraction angiography (DSA) of the lower extremities in patients with peripheral arterial occlusive disease. SUBJECTS AND METHODS. Fifty-one patients with clinically documented peripheral arterial occlusive disease referred for DSA of the lower extremity arterial system underwent whole-body MR angiography on a 1.5-T MR scanner. Paramagnetic gadobutrol was administered and five contiguous stations were acquired with 3D T1-weighted gradient-echo sequences in a total scanning time of 72 sec. DSA was available as a reference standard for the peripheral vasculature in all patients. Separate blinded data analyses were performed by two radiologists. Additional vascular disease detected by whole-body MR angiography was subsequently assessed on sonography, dedicated MR angiography, or both.",
        "journal": "AJR. American journal of roentgenology",
        "year": "2004",
        "authors": [
          "Herborn Christoph U",
          "Goyen Mathias",
          "Quick Harald H",
          "Bosk Silke",
          "Massing Sandra"
        ],
        "pub_types": [
          "Clinical Trial",
          "Comparative Study",
          "Journal Article"
        ],
        "mesh_terms": [
          "Adult",
          "Aged",
          "Angiography, Digital Subtraction",
          "Arterial Occlusive Diseases",
          "Female",
          "Humans",
          "Magnetic Resonance Angiography",
          "Male",
          "Middle Aged",
          "Prospective Studies"
        ],
        "url": "https://pubmed.ncbi.nlm.nih.gov/15149986/"
      },
      {
        "pmid": "25073947",
        "title": "Fusion guidance in endovascular peripheral artery interventions: a feasibility study.",
        "abstract": "This study was designed to evaluate the feasibility of endovascular guidance by means of live fluoroscopy fusion with magnetic resonance angiography (MRA) and computed tomography angiography (CTA).",
        "journal": "Cardiovascular and interventional radiology",
        "year": "2015",
        "authors": [
          "Sailer Anna M",
          "de Haan Michiel W",
          "de Graaf Rick",
          "van Zwam Willem H",
          "Schurink Geert Willem H"
        ],
        "pub_types": [
          "Journal Article"
        ],
        "mesh_terms": [
          "Aged",
          "Aged, 80 and over",
          "Contrast Media",
          "Endovascular Procedures",
          "Feasibility Studies",
          "Female",
          "Femoral Artery",
          "Fluoroscopy",
          "Humans",
          "Iliac Artery"
        ],
        "url": "https://pubmed.ncbi.nlm.nih.gov/25073947/"
      },
      {
        "pmid": "15280530",
        "title": "Gadolinium-based contrast media compared with iodinated media for digital subtraction angiography in azotaemic patients.",
        "abstract": "To determine whether gadolinium-based contrast media (CM) could be used safely for angiographies in patients with renal dysfunction we investigated renal function after gadobutrol exposure and compared the results with standard iodinated CM (iohexol) in a randomized clinical study.",
        "journal": "Nephrology, dialysis, transplantation : official publication of the European Dialysis and Transplant Association - European Renal Association",
        "year": "2004",
        "authors": [
          "Erley Christiane M",
          "Bader Birgit D",
          "Berger Elke D",
          "Tuncel Nurdan",
          "Winkler Sabine"
        ],
        "pub_types": [
          "Clinical Trial",
          "Journal Article",
          "Randomized Controlled Trial"
        ],
        "mesh_terms": [
          "Aged",
          "Angiography, Digital Subtraction",
          "Aortic Aneurysm",
          "Contrast Media",
          "Double-Blind Method",
          "Female",
          "Gadolinium",
          "Glomerular Filtration Rate",
          "Humans",
          "Iohexol"
        ],
        "url": "https://pubmed.ncbi.nlm.nih.gov/15280530/"
      },
      {
        "pmid": "23188773",
        "title": "Comparison of contrast-enhanced multi-station MR angiography and digital subtraction angiography of the lower extremity arterial disease.",
        "abstract": "To compare diagnostic accuracy of multi-station, high-spatial resolution contrast-enhanced MR angiography (CE-MRA) of the lower extremities with digital subtraction angiography (DSA) as the reference standard in patients with symptomatic peripheral arterial occlusive disease.",
        "journal": "Journal of magnetic resonance imaging : JMRI",
        "year": "2013",
        "authors": [
          "Burbelko Mykhaylo",
          "Augsten Michael",
          "Kalinowski Marc O",
          "Heverhagen Johannes T"
        ],
        "pub_types": [
          "Comparative Study",
          "Journal Article"
        ],
        "mesh_terms": [
          "Aged",
          "Angiography, Digital Subtraction",
          "Arterial Occlusive Diseases",
          "Contrast Media",
          "Female",
          "Humans",
          "Lower Extremity",
          "Magnetic Resonance Angiography",
          "Male",
          "Organometallic Compounds"
        ],
        "url": "https://pubmed.ncbi.nlm.nih.gov/23188773/"
      },
      {
        "pmid": "30847564",
        "title": "MR venography using time-resolved imaging in interventional management of pelvic venous insufficiency.",
        "abstract": "To evaluate the utility of magnetic resonance venography with time-resolved imaging (MRV TRI) in the diagnosis of pelvic vein insufficiency (PVI).",
        "journal": "Abdominal radiology (New York)",
        "year": "2019",
        "authors": [
          "Chennur Vikash S",
          "Nzekwu Emeka V",
          "Bhayana Deepak",
          "Raber Earl L",
          "Wong Jason K"
        ],
        "pub_types": [
          "Journal Article",
          "Research Support, Non-U.S. Gov't"
        ],
        "mesh_terms": [
          "Contrast Media",
          "Endovascular Procedures",
          "Gadolinium",
          "Humans",
          "Imaging, Three-Dimensional",
          "Magnetic Resonance Angiography",
          "May-Thurner Syndrome",
          "Organometallic Compounds",
          "Pelvis",
          "Retrospective Studies"
        ],
        "url": "https://pubmed.ncbi.nlm.nih.gov/30847564/"
      },
      {
        "pmid": "12928957",
        "title": "Safety of contrast-enhanced MR angiography employing gadobutrol 1.0 M as contrast material.",
        "abstract": "Our objectives were to evaluate the safety of intravenous 1.0-M gadobutrol injections in patients with an indication for contrast-enhanced magnetic resonance angiography (CE MRA) of supra-aortal, pelvic, or peripheral arteries by examining and assessing adverse events, laboratory values, vital signs and ECG findings for clinical significance. In 435 patients, recruited in three multicenter trials for safety evaluations of the new contrast agent 1.0-M gadobutrol, CE MRA was performed with 1.0- to 1.5-T scanners using three-dimensional gradient-echo sequences and phased-array coils. The study population comprised 312 men and 123 women with a mean age of 60.9 years. Two hundred seven patients had an indication for imaging of body arteries and 228 had an indication for imaging of peripheral arteries. Blood laboratory values and urinalysis results of 124 patients as well as heart rate, blood pressure, and 12-lead-electrocardiogram readings of 93 patients obtained during a follow-up period o",
        "journal": "European radiology",
        "year": "2003",
        "authors": [
          "Balzer Jörn O",
          "Loewe Christian",
          "Davis Kirsten",
          "Goyen Mathias",
          "Leiner Tim"
        ],
        "pub_types": [
          "Journal Article",
          "Multicenter Study"
        ],
        "mesh_terms": [
          "Adult",
          "Aged",
          "Blood Pressure",
          "Contrast Media",
          "Creatinine",
          "Electrocardiography",
          "Female",
          "Heart Rate",
          "Humans",
          "Injections, Intravenous"
        ],
        "url": "https://pubmed.ncbi.nlm.nih.gov/12928957/"
      },
      {
        "pmid": "12720266",
        "title": "Using a 1 M Gd-chelate (gadobutrol) for total-body three-dimensional MR angiography: preliminary experience.",
        "abstract": "To determine whether higher concentrated gadolinium chelates are advantageous for the recently introduced concept of total-body magnetic resonance angiography (MRA), allowing whole-body coverage, extending from the carotid arteries to the runoff vessels, in merely 72 seconds.",
        "journal": "Journal of magnetic resonance imaging : JMRI",
        "year": "2003",
        "authors": [
          "Goyen Mathias",
          "Herborn Christoph U",
          "Vogt Florian M",
          "Kröger Knut",
          "Verhagen Rüdiger"
        ],
        "pub_types": [
          "Journal Article"
        ],
        "mesh_terms": [
          "Adult",
          "Aged",
          "Aged, 80 and over",
          "Aorta, Thoracic",
          "Arteriosclerosis",
          "Carotid Arteries",
          "Contrast Media",
          "Female",
          "Humans",
          "Image Processing, Computer-Assisted"
        ],
        "url": "https://pubmed.ncbi.nlm.nih.gov/12720266/"
      },
      {
        "pmid": "20706840",
        "title": "High-resolution 3D non-contrast-enhanced, ECG-gated, multi-step MR angiography of the lower extremities: comparison with contrast-enhanced MR angiography.",
        "abstract": "To determine the diagnostic value of non-contrast-enhanced, 3D-high-resolution, ECG-gated, multi-step MR angiography (non-ceMRA) of the lower extremities using a modified turbo-spin-echo technique in comparison to 1.0-molar contrast-enhanced MR angiography (ceMRA) in patients with suspected peripheral vascular disease (PVD).",
        "journal": "European radiology",
        "year": "2011",
        "authors": [
          "Mohrs Oliver K",
          "Petersen Steffen E",
          "Heidt Martin C",
          "Schulze Thomas",
          "Schmitt Peter"
        ],
        "pub_types": [
          "Comparative Study",
          "Evaluation Study",
          "Journal Article",
          "Research Support, Non-U.S. Gov't"
        ],
        "mesh_terms": [
          "Adult",
          "Aged",
          "Atherosclerosis",
          "Cardiac-Gated Imaging Techniques",
          "Contrast Media",
          "Electrocardiography",
          "Female",
          "Humans",
          "Image Enhancement",
          "Imaging, Three-Dimensional"
        ],
        "url": "https://pubmed.ncbi.nlm.nih.gov/20706840/"
      }
    ]
  },
  "timestamp": "2026-03-10T10:34:23.839519",
  "success": true,
  "error_message": null
}