{
  "source": "pubmed",
  "query": {
    "drug": "Glycopyrronium",
    "disease": "irritable bowel syndrome",
    "query_string": "Glycopyrronium AND irritable bowel syndrome"
  },
  "data": {
    "query": "Glycopyrronium AND irritable bowel syndrome",
    "results": [
      {
        "pmid": "9696463",
        "title": "Effects of tricyclic antidepressants on mechanosensitive pelvic nerve afferent fibers innervating the rat colon.",
        "abstract": "The aim of this study was to examine the effects of tricyclic antidepressants on responses of mechanosensitive afferent fibers innervating the rat colon. A total of 53 fibers in the decentralized S1 dorsal root were studied. The effects of the non-specific monoamine reuptake inhibitor imipramine (IMI), the noradrenaline reuptake inhibitor desipramine (DES), and the serotonin reuptake inhibitor clomipramine (CLO) were tested on responses of 22 mechanosensitive afferent fibers to noxious colorectal distension (CRD; 80 mmHg). Cumulative doses of 16 mg/kg of IMI, DES and of CLO reduced responses to noxious CRD to a mean 20%, 22% and 46% of control, respectively. The mean inhibitory doses of the three antidepressants did not differ significantly. Inhibitory effects were independent of potential effects on neurotransmitter reuptake: the effects of IMI and DES were not blocked by the adrenoreceptor antagonist phentolamine, and the effects of IMI and CLO were not affected by the serotonin rece",
        "journal": "Pain",
        "year": "1998",
        "authors": [
          "Su X",
          "Gebhart G F"
        ],
        "pub_types": [
          "Journal Article",
          "Research Support, Non-U.S. Gov't",
          "Research Support, U.S. Gov't, P.H.S."
        ],
        "mesh_terms": [
          "Action Potentials",
          "Animals",
          "Antidepressive Agents, Tricyclic",
          "Cholinergic Antagonists",
          "Colon",
          "Dose-Response Relationship, Drug",
          "In Vitro Techniques",
          "Male",
          "Mechanoreceptors",
          "Muscle, Smooth"
        ],
        "url": "https://pubmed.ncbi.nlm.nih.gov/9696463/"
      }
    ]
  },
  "timestamp": "2026-03-10T06:23:35.619255",
  "success": true,
  "error_message": null
}