{
  "source": "pubmed",
  "query": {
    "drug": "Insulin aspart",
    "disease": "permanent neonatal diabetes mellitus",
    "query_string": "Insulin aspart AND permanent neonatal diabetes mellitus"
  },
  "data": {
    "query": "Insulin aspart AND permanent neonatal diabetes mellitus",
    "results": [
      {
        "pmid": "28527303",
        "title": "Insulin therapy in neonatal diabetes mellitus: a review of the literature.",
        "abstract": "Neonatal diabetes mellitus (NDM) is a rare disorder, and guidance is limited regarding its optimal management. We reviewed insulin usage in NDM, with a focus on continuous subcutaneous insulin infusion (CSII).",
        "journal": "Diabetes research and clinical practice",
        "year": "2017",
        "authors": [
          "Rabbone Ivana",
          "Barbetti Fabrizio",
          "Gentilella Raffaella",
          "Mossetto Gilberto",
          "Bonfanti Riccardo"
        ],
        "pub_types": [
          "Journal Article",
          "Review"
        ],
        "mesh_terms": [
          "Diabetes Mellitus, Type 1",
          "Female",
          "Humans",
          "Hypoglycemic Agents",
          "Infant, Newborn",
          "Insulin",
          "Insulin Infusion Systems",
          "Male"
        ],
        "url": "https://pubmed.ncbi.nlm.nih.gov/28527303/"
      }
    ]
  },
  "timestamp": "2026-03-09T13:51:59.050290",
  "success": true,
  "error_message": null
}