{
  "source": "pubmed",
  "query": {
    "drug": "Labetalol",
    "disease": "atrial flutter (disease)",
    "query_string": "Labetalol AND atrial flutter (disease)"
  },
  "data": {
    "query": "Labetalol AND atrial flutter (disease)",
    "results": [
      {
        "pmid": "6145367",
        "title": "Beta-blocking drugs for arrhythmias, hypertension, and ischemic heart disease.",
        "abstract": "Beta-blocking drugs have provided significant improvement in the medical therapy of many types of heart disease. They are more effective in treating young hypertensive patients than elderly hypertensive patients. These drugs reduce the ventricular rate seen in atrial flutter and fibrillation, and they also reduce the frequency of ventricular ectopy. Beta blockers are important adjuncts for control of angina pectoris. When these drugs are given for a period of 1 to 3 years after myocardial infarction they reduce the incidence of reinfarction and the frequency of sudden death as well as reduce the overall mortality rate. Factors that may contribute to the overall decreased mortality include the reduction in the reinfarction rate and an increased threshold for ventricular fibrillation as well as those mechanisms that reduce myocardial oxygen utilization.",
        "journal": "American journal of surgery",
        "year": "1984",
        "authors": [
          "Johns V J"
        ],
        "pub_types": [
          "Journal Article",
          "Review"
        ],
        "mesh_terms": [
          "Adrenergic beta-Antagonists",
          "Angina Pectoris",
          "Animals",
          "Arrhythmias, Cardiac",
          "Atenolol",
          "Blood Pressure",
          "Coronary Disease",
          "Dogs",
          "Heart Rate",
          "Humans"
        ],
        "url": "https://pubmed.ncbi.nlm.nih.gov/6145367/"
      }
    ]
  },
  "timestamp": "2026-03-10T05:36:55.328076",
  "success": true,
  "error_message": null
}