{
  "source": "pubmed",
  "query": {
    "drug": "Megestrol acetate",
    "disease": "placenta cancer",
    "query_string": "Megestrol acetate AND placenta cancer"
  },
  "data": {
    "query": "Megestrol acetate AND placenta cancer",
    "results": [
      {
        "pmid": "7626488",
        "title": "Estrone sulfate-sulfatase and 17 beta-hydroxysteroid dehydrogenase activities: a hypothesis for their role in the evolution of human breast cancer from hormone-dependence to hormone-independence.",
        "abstract": "The evaluation of estrogens (estrone, estradiol, and their sulfates) in the breast tissue of post-menopausal patients with breast cancer indicates high levels, particularly of estrone sulfate (E1S) which is 15-25 times higher than in the plasma. Breast cancer tissue contains the enzymes necessary for local synthesis of estradiol and it was demonstrated that, despite the presence of the sulfatase and its messenger in hormone-dependent and hormone-independent breast cancer cells, this enzyme operates particularly in hormone-dependent cells. Different progestins: Nomegestrol acetate, Promegestone, progesterone, as well as Danazol, can block the conversion of E1S to E2 very strongly in hormone-dependent breast cancer cells. The last step in the formation of estradiol is the conversion of E1 to this estrogen by the action of 17 beta-hydroxysteroid dehydrogenase. This activity is preferentially in the reductive direction (formation of E2) in hormone-dependent cells, but oxidative (E2-->E1) i",
        "journal": "The Journal of steroid biochemistry and molecular biology",
        "year": "1995",
        "authors": [
          "Pasqualini J R",
          "Chetrite G",
          "Nguyen B L",
          "Maloche C",
          "Delalonde L"
        ],
        "pub_types": [
          "Journal Article",
          "Research Support, Non-U.S. Gov't"
        ],
        "mesh_terms": [
          "17-Hydroxysteroid Dehydrogenases",
          "Breast Neoplasms",
          "Estrogens",
          "Estrone",
          "Female",
          "Gene Expression Regulation, Neoplastic",
          "Humans",
          "In Vitro Techniques",
          "Megestrol",
          "Placenta"
        ],
        "url": "https://pubmed.ncbi.nlm.nih.gov/7626488/"
      }
    ]
  },
  "timestamp": "2026-03-09T14:30:41.209660",
  "success": true,
  "error_message": null
}