{
  "source": "pubmed",
  "query": {
    "drug": "Nicotine",
    "disease": "blepharospasm",
    "query_string": "Nicotine AND blepharospasm"
  },
  "data": {
    "query": "Nicotine AND blepharospasm",
    "results": [
      {
        "pmid": "11549226",
        "title": "Human studies of prepulse inhibition of startle: normal subjects, patient groups, and pharmacological studies.",
        "abstract": "Since the mid-1970s, cross-species translational studies of prepulse inhibition (PPI) have increased at an astounding pace as the value of this neurobiologically informative measure has been optimized. PPI occurs when a relatively weak sensory event (the prepulse) is presented 30-500 ms before a strong startle-inducing stimulus, and reduces the magnitude of the startle response. In humans, PPI occurs in a robust, predictable manner when the prepulse and startling stimuli occur in either the same or different modalities (acoustic, visual, or cutaneous).",
        "journal": "Psychopharmacology",
        "year": "2001",
        "authors": [
          "Braff D L",
          "Geyer M A",
          "Swerdlow N R"
        ],
        "pub_types": [
          "Journal Article",
          "Research Support, U.S. Gov't, Non-P.H.S.",
          "Research Support, U.S. Gov't, P.H.S.",
          "Review"
        ],
        "mesh_terms": [
          "Humans",
          "Mental Disorders",
          "Psychotropic Drugs",
          "Reflex, Startle",
          "Schizophrenic Psychology"
        ],
        "url": "https://pubmed.ncbi.nlm.nih.gov/11549226/"
      },
      {
        "pmid": "9452355",
        "title": "Nicotine nasal spray is not reliable treatment for blepharospasm: results of a pilot study.",
        "abstract": "",
        "journal": "Movement disorders : official journal of the Movement Disorder Society",
        "year": "1998",
        "authors": [
          "Dressler D",
          "Scaravilli T",
          "Bhatia K P",
          "Marsden C D"
        ],
        "pub_types": [
          "Clinical Trial",
          "Journal Article"
        ],
        "mesh_terms": [
          "Aerosols",
          "Blepharospasm",
          "Ganglionic Stimulants",
          "Humans",
          "Longitudinal Studies",
          "Nicotine",
          "Pilot Projects",
          "Treatment Outcome"
        ],
        "url": "https://pubmed.ncbi.nlm.nih.gov/9452355/"
      },
      {
        "pmid": "8691949",
        "title": "Treatment of blepharospasm with nicotine nasal spray.",
        "abstract": "",
        "journal": "Lancet (London, England)",
        "year": "1996",
        "authors": [
          "Dursun S M",
          "Hewitt S",
          "King A L",
          "Reveley M A"
        ],
        "pub_types": [
          "Case Reports",
          "Letter"
        ],
        "mesh_terms": [
          "Administration, Intranasal",
          "Aerosols",
          "Blepharospasm",
          "Humans",
          "Male",
          "Middle Aged",
          "Nicotine"
        ],
        "url": "https://pubmed.ncbi.nlm.nih.gov/8691949/"
      }
    ]
  },
  "timestamp": "2026-03-10T09:16:27.145837",
  "success": true,
  "error_message": null
}