{
  "source": "pubmed",
  "query": {
    "drug": "Prilocaine",
    "disease": "migraine disorder",
    "query_string": "Prilocaine AND migraine disorder"
  },
  "data": {
    "query": "Prilocaine AND migraine disorder",
    "results": [
      {
        "pmid": "37400308",
        "title": "Decreased role of neuropeptides in the microvascular function in migraine patients with polycystic ovary syndrome.",
        "abstract": "To understand pathophysiological mechanisms underlying migraine as a cardiovascular risk factor, we studied neuropeptide action and endothelial function as measures of peripheral microvascular function in middle-aged women with or without migraine.",
        "journal": "Atherosclerosis",
        "year": "2023",
        "authors": [
          "Al-Hassany Linda",
          "Linstra Katie M",
          "Meun Cindy",
          "van den Berg Jeffrey",
          "Boersma Eric"
        ],
        "pub_types": [
          "Journal Article",
          "Research Support, Non-U.S. Gov't"
        ],
        "mesh_terms": [
          "Middle Aged",
          "Humans",
          "Female",
          "omega-N-Methylarginine",
          "Polycystic Ovary Syndrome",
          "Vasodilation",
          "Risk Factors",
          "Migraine Disorders"
        ],
        "url": "https://pubmed.ncbi.nlm.nih.gov/37400308/"
      }
    ]
  },
  "timestamp": "2026-03-09T21:56:11.704963",
  "success": true,
  "error_message": null
}