{
  "source": "pubmed",
  "query": {
    "drug": "Sorafenib",
    "disease": "unclassified renal cell carcinoma",
    "query_string": "Sorafenib AND unclassified renal cell carcinoma"
  },
  "data": {
    "query": "Sorafenib AND unclassified renal cell carcinoma",
    "results": [
      {
        "pmid": "30268423",
        "title": "Carcinoma of Unknown Primary Site (CUP) With Metastatic Renal-Cell Carcinoma (mRCC) Histologic and Immunohistochemical Characteristics (CUP-mRCC): Results From Consecutive Patients Treated With Targeted Therapy and Review of Literature.",
        "abstract": "Carcinoma of unknown primary site (CUP) is a heterogenous group of metastatic cancer with no detectable primary tumor site. Diagnostic assessment occasionally presents CUP with metastatic renal-cell carcinoma (mRCC) histologic and immunohistochemical characteristics (CUP-mRCC). Efficacy and toxicity data for vascular endothelial growth factor inhibitor therapies in CUP-mRCC patients are few.",
        "journal": "Clinical genitourinary cancer",
        "year": "2019",
        "authors": [
          "Overby Anders",
          "Duval Lone",
          "Ladekarl Morten",
          "Laursen Britt Elmedal",
          "Donskov Frede"
        ],
        "pub_types": [
          "Journal Article",
          "Review"
        ],
        "mesh_terms": [
          "Aged",
          "Carcinoma, Papillary",
          "Carcinoma, Renal Cell",
          "Female",
          "Follow-Up Studies",
          "Humans",
          "Immunohistochemistry",
          "Kidney Neoplasms",
          "Lymphatic Metastasis",
          "Male"
        ],
        "url": "https://pubmed.ncbi.nlm.nih.gov/30268423/"
      },
      {
        "pmid": "20845054",
        "title": "Combination therapy with sorafenib and S-1 for renal cell carcinoma producing granulocyte colony-stimulating factor.",
        "abstract": "We present the first case report of the use of sorafenib and S-1 for the treatment of renal cell carcinoma (RCC) producing granulocyte colony-stimulating factor (G-CSF). This entity is clinically rare and has a poor outcome. A 78-year-old Japanese man presented with macrohematuria, left flank pain, and a palpable mass. Laboratory data showed marked leukocytosis with increased serum and urinary G-CSF. The histopathological diagnosis was unclassified RCC. New combination therapy with sorafenib and S-1 exerted a therapeutic effect and apparently decreased serum and urinary G-CSF levels, although the patient died of gastrointestinal perforation. The use of combined sorafenib and S-1 may be worthy of consideration in the treatment of RCC producing G-CSF.",
        "journal": "International journal of clinical oncology",
        "year": "2011",
        "authors": [
          "Kyono Yoko",
          "Takayama Tatsuya",
          "Kinoshita Mana",
          "Kurita Yutaka",
          "Mugiya Soichi"
        ],
        "pub_types": [
          "Case Reports",
          "Journal Article"
        ],
        "mesh_terms": [
          "Aged",
          "Antineoplastic Combined Chemotherapy Protocols",
          "Benzenesulfonates",
          "Carcinoma, Renal Cell",
          "Drug Combinations",
          "Granulocyte Colony-Stimulating Factor",
          "Humans",
          "Kidney Neoplasms",
          "Leukocytosis",
          "Male"
        ],
        "url": "https://pubmed.ncbi.nlm.nih.gov/20845054/"
      },
      {
        "pmid": "19616232",
        "title": "Surgical resection of renal cell carcinoma after targeted therapy.",
        "abstract": "The development of targeted agents for renal cell carcinoma has renewed interest in consolidative surgery due to the robust clinical responses seen with these agents. The integration of targeted therapy and surgery requires careful consideration due to the potential for increased perioperative morbidity.",
        "journal": "The Journal of urology",
        "year": "2009",
        "authors": [
          "Thomas Anil A",
          "Rini Brian I",
          "Stephenson Andrew J",
          "Garcia Jorge A",
          "Fergany Amr"
        ],
        "pub_types": [
          "Journal Article"
        ],
        "mesh_terms": [
          "Adult",
          "Aged",
          "Aged, 80 and over",
          "Angiogenesis Inhibitors",
          "Antibodies, Monoclonal",
          "Antibodies, Monoclonal, Humanized",
          "Antineoplastic Combined Chemotherapy Protocols",
          "Benzenesulfonates",
          "Bevacizumab",
          "Carcinoma, Renal Cell"
        ],
        "url": "https://pubmed.ncbi.nlm.nih.gov/19616232/"
      }
    ]
  },
  "timestamp": "2026-03-09T20:51:33.398201",
  "success": true,
  "error_message": null
}