{
  "source": "pubmed",
  "query": {
    "drug": "Sulfamethoxazole",
    "disease": "parasitic eyelid infestation",
    "query_string": "Sulfamethoxazole AND parasitic eyelid infestation"
  },
  "data": {
    "query": "Sulfamethoxazole AND parasitic eyelid infestation",
    "results": [
      {
        "pmid": "6209693",
        "title": "Pediculosis and the pediatrician.",
        "abstract": "Head lice commonly evoke feelings of disgust, revulsion, anger, and shame among parents and patients. There should, however, be no great cause for such alarm if a physician suspects pediculosis capitis. The recent introduction of several new pediculicidal drugs now allows a choice among four distinct therapeutic agents, which should substantially improve control of isolated cases and epidemics. Physicians must be aware that consumer groups are pressing public health authorities and drug manufacturers to establish proper treatment standards and safety warnings for the use of these agents. In addition, some controversy surrounds the use of lindane in children. This paper reviews the epidemiology and clinical appearance of pediculosis capitis in children, with emphasis on these recent developments. Pubic lice (Phthirus pubis) and body lice (Pediculus humanus corporis), both of which are much less common pediatric infestations, are mentioned only briefly.",
        "journal": "Pediatric dermatology",
        "year": "1984",
        "authors": [
          "Rasmussen J E"
        ],
        "pub_types": [
          "Journal Article"
        ],
        "mesh_terms": [
          "Child",
          "Drug Combinations",
          "Eyelashes",
          "Female",
          "Fluorescein",
          "Fluoresceins",
          "Hexachlorocyclohexane",
          "Humans",
          "Lice Infestations",
          "Malathion"
        ],
        "url": "https://pubmed.ncbi.nlm.nih.gov/6209693/"
      }
    ]
  },
  "timestamp": "2026-03-09T15:44:16.208796",
  "success": true,
  "error_message": null
}