{
  "source": "pubmed",
  "query": {
    "drug": "Valganciclovir",
    "disease": "headache disorder",
    "query_string": "Valganciclovir AND headache disorder"
  },
  "data": {
    "query": "Valganciclovir AND headache disorder",
    "results": [
      {
        "pmid": "11465875",
        "title": "Valganciclovir.",
        "abstract": "Valganciclovir is a prodrug of ganciclovir which has been developed for the treatment of cytomegalovirus (CMV) retinitis in patients with AIDS. Oral valganciclovir is rapidly absorbed and hydrolysed to ganciclovir. The oral bioavailability of ganciclovir after oral valganciclovir administration is high. Oral valganciclovir 900 mg provides a daily exposure of ganciclovir comparable to that of intravenous ganciclovir 5 mg/kg. A single, randomised, nonblind study indicated that oral valganciclovir (900mg twice daily for 3 weeks then 900 mg once daily) and intravenous ganciclovir (5 mg/kg twice daily for 3 weeks then 5 mg/kg once daily) were equally effective in the treatment of newly diagnosed CMV retinitis in 160 patients with AIDS. Valganciclovir appears to have a similar tolerability profile to intravenous ganciclovir during induction therapy in patients with AIDS and newly diagnosed CMV retinitis. During maintenance therapy with valganciclovir, the most commonly reported adverse event",
        "journal": "Drugs",
        "year": "2001",
        "authors": [
          "Curran M",
          "Noble S"
        ],
        "pub_types": [
          "Journal Article"
        ],
        "mesh_terms": [
          "Acquired Immunodeficiency Syndrome",
          "Administration, Oral",
          "Anemia",
          "Antiviral Agents",
          "Biological Availability",
          "Cytomegalovirus Retinitis",
          "Fever",
          "Ganciclovir",
          "Gastrointestinal Diseases",
          "Headache"
        ],
        "url": "https://pubmed.ncbi.nlm.nih.gov/11465875/"
      },
      {
        "pmid": "30267504",
        "title": "Epstein-barr virus-associated encephalitis in a case-series of more than 40 patients.",
        "abstract": "Introduction: Epstein-Barr virus (EBV) infection can present with neurologic manifestations including encephalitis, aseptic meningitis, Guillain-Barre syndrome, and many others. Most reported cases have been in children. Little is known about EBV encephalitis in adults. The aim: To describe the clinical presentations, investigational findings, management and outcome of adult patients with EBV encephalitis.",
        "journal": "Wiadomosci lekarskie (Warsaw, Poland : 1960)",
        "year": "2018",
        "authors": [
          "Dyachenko Pavel",
          "Smiianova Olha",
          "Kurhanskaya Victoria",
          "Oleshko Alexander",
          "Dyachenko Anatoly"
        ],
        "pub_types": [
          "Journal Article"
        ],
        "mesh_terms": [
          "Adult",
          "Encephalitis",
          "Epstein-Barr Virus Infections",
          "Herpesvirus 4, Human",
          "Humans",
          "Retrospective Studies",
          "Ukraine"
        ],
        "url": "https://pubmed.ncbi.nlm.nih.gov/30267504/"
      },
      {
        "pmid": "23516318",
        "title": "Human herpes 6 virus encephalitis complicating allogeneic hematopoietic stem cell transplantation.",
        "abstract": "To describe the presentation and management of encephalitis due to human herpes 6 virus (HHV-6) in patients who underwent allogeneic hematopoietic stem cell transplant (alloHSCT), via retrospective chart review.",
        "journal": "Neurology",
        "year": "2013",
        "authors": [
          "Bhanushali Minal J",
          "Kranick Sarah M",
          "Freeman Alexandra F",
          "Cuellar-Rodriguez Jennifer M",
          "Battiwalla Minoo"
        ],
        "pub_types": [
          "Journal Article",
          "Research Support, N.I.H., Intramural"
        ],
        "mesh_terms": [
          "Adult",
          "Aged",
          "Antiviral Agents",
          "Brain",
          "Disease Progression",
          "Female",
          "Follow-Up Studies",
          "Headache",
          "Hematologic Neoplasms",
          "Hematopoietic Stem Cell Transplantation"
        ],
        "url": "https://pubmed.ncbi.nlm.nih.gov/23516318/"
      }
    ]
  },
  "timestamp": "2026-03-10T06:02:25.457506",
  "success": true,
  "error_message": null
}