{
  "resourceType": "MedicationKnowledge",
  "id": "db00668",
  "meta": {
    "profile": [
      "http://hl7.org/fhir/StructureDefinition/MedicationKnowledge"
    ]
  },
  "status": "active",
  "code": {
    "coding": [
      {
        "system": "https://go.drugbank.com/drugs",
        "code": "DB00668",
        "display": "Epinephrine"
      }
    ],
    "text": "Epinephrine"
  },
  "synonym": [
    "CITOCARTIN 100 INJECTION 1.7 ml/cartridge"
  ],
  "intendedJurisdiction": [
    {
      "coding": [
        {
          "system": "urn:iso:std:iso:3166",
          "code": "SG",
          "display": "Singapore"
        }
      ]
    }
  ],
  "regulatory": [
    {
      "regulatoryAuthority": {
        "display": "Singapore Health Sciences Authority (HSA)"
      },
      "identifier": [
        {
          "system": "https://sgtxgnn.yao.care/hsa-license",
          "value": "SIN12648P"
        }
      ]
    }
  ],
  "extension": [
    {
      "url": "https://sgtxgnn.yao.care/fhir/StructureDefinition/prediction-source",
      "valueString": "TxGNN Knowledge Graph"
    }
  ]
}