{
  "resourceType": "MedicationKnowledge",
  "id": "db09141",
  "meta": {
    "profile": [
      "http://hl7.org/fhir/StructureDefinition/MedicationKnowledge"
    ]
  },
  "status": "active",
  "code": {
    "coding": [
      {
        "system": "https://go.drugbank.com/drugs",
        "code": "DB09141",
        "display": "Protamine sulfate"
      }
    ],
    "text": "Protamine sulfate"
  },
  "synonym": [
    "PROSULF INJECTION 1%"
  ],
  "intendedJurisdiction": [
    {
      "coding": [
        {
          "system": "urn:iso:std:iso:3166",
          "code": "SG",
          "display": "Singapore"
        }
      ]
    }
  ],
  "regulatory": [
    {
      "regulatoryAuthority": {
        "display": "Singapore Health Sciences Authority (HSA)"
      },
      "identifier": [
        {
          "system": "https://sgtxgnn.yao.care/hsa-license",
          "value": "SIN03696P"
        }
      ]
    }
  ],
  "extension": [
    {
      "url": "https://sgtxgnn.yao.care/fhir/StructureDefinition/prediction-source",
      "valueString": "TxGNN Knowledge Graph"
    }
  ]
}